gpack/Converter.py
gpack/__init__.py
gpack/deep_hexlib.py
gpack-0.1.6.dist-info/licenses/LICENSE
gpack-0.1.6.dist-info/METADATA
gpack-0.1.6.dist-info/WHEEL
gpack-0.1.6.dist-info/top_level.txt
gpack-0.1.6.dist-info/RECORD
