Metadata-Version: 2.4
Name: gpack
Version: 0.1.6
Summary: GPack is struct analog and better!
Author-email: GPGStudio <gpgstudio.original@gmail.com>
License: MIT
Project-URL: Homepage, https://github.com/GPGSTUDIO/GPack
Project-URL: Repository, https://github.com/GPGSTUDIO/GPack
Project-URL: Bug Reports, https://github.com/GPGSTUDIO/GPack/issues
Keywords: GPack,binary,struct,decimal,binary,string,
Classifier: Development Status :: 3 - Alpha
Classifier: Intended Audience :: Developers
Classifier: License :: OSI Approved :: MIT License
Classifier: Programming Language :: Python :: 3.10
Classifier: Programming Language :: Python :: 3.11
Classifier: Programming Language :: Python :: 3.12
Classifier: Programming Language :: Python :: 3.13
Classifier: Programming Language :: Python :: 3.14
License-File: LICENSE
Provides-Extra: dev
Requires-Dist: pytest>=7.0; extra == "dev"
Requires-Dist: black; extra == "dev"
Requires-Dist: flake8; extra == "dev"
Dynamic: license-file
